proteusPy/CHANGELOG.md
proteusPy/Disulfide.py
proteusPy/DisulfideBase.py
proteusPy/DisulfideClassGenerator.py
proteusPy/DisulfideClassManager.py
proteusPy/DisulfideClass_Constructor.py
proteusPy/DisulfideClasses.py
proteusPy/DisulfideEnergy.py
proteusPy/DisulfideExceptions.py
proteusPy/DisulfideExtractor_mp.py
proteusPy/DisulfideIO.py
proteusPy/DisulfideList.py
proteusPy/DisulfideLoader.py
proteusPy/DisulfideStats.py
proteusPy/DisulfideVisualization.py
proteusPy/LICENSE
proteusPy/Plotting.py
proteusPy/ProteusGlobals.py
proteusPy/ProteusPyWarning.py
proteusPy/Residue.py
proteusPy/__init__.py
proteusPy/_version.py
proteusPy/angle_annotation.py
proteusPy/atoms.py
proteusPy/bootstrapper.py
proteusPy/display_class_disulfides.py
proteusPy/disulfide_schematic.py
proteusPy/generate_class_disulfides.py
proteusPy/hexbin_plot.py
proteusPy/logger_config.py
proteusPy/oDisulfideList.py
proteusPy/qt5viewer.py
proteusPy/render_disulfide_schematic.py
proteusPy/ssparser.py
proteusPy/turtle3D.py
proteusPy/utility.py
proteusPy/vector3D.py
proteusPy/data/2q7q_seqsim.csv
proteusPy/data/PDB_SS_class_definitions.csv
proteusPy/data/SS_consensus_class_32.pkl
proteusPy/data/SS_consensus_class_oct.pkl
proteusPy/data/binary_class_metrics.pkl
proteusPy/data/octant_class_metrics.pkl
proteusPy/data/pdb5rsa.ent
proteusPy/data/ss_completed.txt
proteusPy/data/ss_ids.txt
proteusPy/data/ss_query.json
proteuspy-0.99.35.dist-info/licenses/LICENSE
tests/Test_DisplaySS.py
tests/__init__.py
tests/test_disulfide.py
tests/test_disulfidelist.py
tests/test_turtle3d.py
proteuspy-0.99.35.dist-info/METADATA
proteuspy-0.99.35.dist-info/WHEEL
proteuspy-0.99.35.dist-info/entry_points.txt
proteuspy-0.99.35.dist-info/top_level.txt
proteuspy-0.99.35.dist-info/RECORD
