Metadata-Version: 2.4
Name: proteusPy
Version: 0.99.35
Summary: proteusPy - Protein Structure Analysis and Modeling Tools
Author-email: "Eric G. Suchanek, PhD" <suchanek@mac.com>
License: BSD
Project-URL: Documentation, https://suchanek.github.io/proteusPy/
Project-URL: Source, https://github.com/suchanek/proteusPy/
Project-URL: Tracker, https://github.com/suchanek/proteusPy/issues
Keywords: proteusPy,suchanek,disulfide
Classifier: Development Status :: 4 - Beta
Classifier: License :: OSI Approved :: BSD License
Classifier: Intended Audience :: Developers
Classifier: Intended Audience :: Science/Research
Classifier: Operating System :: OS Independent
Classifier: Programming Language :: Python :: 3.12
Classifier: Topic :: Scientific/Engineering
Classifier: Topic :: Scientific/Engineering :: Bio-Informatics
Classifier: Topic :: Scientific/Engineering :: Chemistry
Requires-Python: >=3.12
License-File: LICENSE
Requires-Dist: Biopython
Requires-Dist: colorama==0.4.6
Requires-Dist: darkdetect==0.8.0
Requires-Dist: gdown==5.2.0
Requires-Dist: imageio[ffmpeg]
Requires-Dist: jupyter==1.1.1
Requires-Dist: notebook==7.2.2
Requires-Dist: nbconvert
Requires-Dist: ipykernel
Requires-Dist: ipywidgets
Requires-Dist: jupyter_bokeh==4.0.5
Requires-Dist: jupyter_contrib_nbextensions
Requires-Dist: kaleido
Requires-Dist: matplotlib==3.9.2
Requires-Dist: numpy
Requires-Dist: pandas
Requires-Dist: panel==1.5.3
Requires-Dist: param==2.1.1
Requires-Dist: Pillow==11.0.0
Requires-Dist: plotly==5.24.1
Requires-Dist: plotly_express==0.4.1
Requires-Dist: psutil
Requires-Dist: pymolPy3==0.1.2
Requires-Dist: Pympler==1.1
Requires-Dist: pyvista[all]
Requires-Dist: Requests==2.32.3
Requires-Dist: scipy==1.14.1
Requires-Dist: seaborn==0.13.2
Requires-Dist: setuptools
Requires-Dist: tabulate
Requires-Dist: tqdm==4.67.0
Requires-Dist: trame-jupyter-extension==2.1.3
Requires-Dist: vtk
Requires-Dist: wheel
Requires-Dist: networkx
Requires-Dist: rich
Provides-Extra: dev
Requires-Dist: pytest; extra == "dev"
Requires-Dist: coverage; extra == "dev"
Requires-Dist: twine; extra == "dev"
Requires-Dist: pdoc; extra == "dev"
Requires-Dist: wheel; extra == "dev"
Requires-Dist: build; extra == "dev"
Provides-Extra: bio
Requires-Dist: Biopython; extra == "bio"
Provides-Extra: pyqt5
Requires-Dist: pyqt5; extra == "pyqt5"
Requires-Dist: pyvistaqt; extra == "pyqt5"
Provides-Extra: all
Requires-Dist: pytest; extra == "all"
Requires-Dist: coverage; extra == "all"
Requires-Dist: twine; extra == "all"
Requires-Dist: pdoc; extra == "all"
Requires-Dist: Biopython; extra == "all"
Requires-Dist: pyqt5; extra == "all"
Requires-Dist: pyvistaqt; extra == "all"
Requires-Dist: wheel; extra == "all"
Requires-Dist: build; extra == "all"
Requires-Dist: networkx; extra == "all"
Dynamic: license-file
